pyramid_handy/__init__.py
pyramid_handy/tweens/__init__.py
pyramid_handy/tweens/allow_origin.py
pyramid_handy/tweens/api_headers.py
pyramid_handy/tweens/basic_auth.py
pyramid_handy-0.2.1.dist-info/DESCRIPTION.rst
pyramid_handy-0.2.1.dist-info/METADATA
pyramid_handy-0.2.1.dist-info/metadata.json
pyramid_handy-0.2.1.dist-info/RECORD
pyramid_handy-0.2.1.dist-info/top_level.txt
pyramid_handy-0.2.1.dist-info/WHEEL
